liberator/__init__.py
liberator/core.py
liberator/core.pyi
liberator/py.typed
liberator/starfinder.py
liberator/starfinder.pyi
liberator-0.1.1.dist-info/LICENSE
liberator-0.1.1.dist-info/METADATA
liberator-0.1.1.dist-info/WHEEL
liberator-0.1.1.dist-info/top_level.txt
liberator-0.1.1.dist-info/RECORD
